Gangler/__init__.py
Gangler/pool.py
Gangler/prepare.py
genetorch/__init__.py
genetorch/apf.py
genetorch/finder.py
genetorch/genelist.py
genetorch/mimo.py
genetorch/pcluster.py
genetorch/reader.py
genetorch/simulator.py
genetorch/stocker.py
genetorch/wormbase.py
genetorch-1.3.3.dist-info/LICENSE
genetorch-1.3.3.dist-info/METADATA
genetorch-1.3.3.dist-info/WHEEL
genetorch-1.3.3.dist-info/top_level.txt
genetorch-1.3.3.dist-info/RECORD
