Metadata-Version: 2.1
Name: genetorch
Version: 1.3.3
Summary: To deal with large amount of WGS data in suppressor screening and to predict suppressor gene
Author: Guo_Zhengyang
Author-email: guozhengyang980525@yahoo.co.jp
License: MIT License
Platform: all
Classifier: Programming Language :: Python :: 3
Classifier: Development Status :: 4 - Beta
License-File: LICENSE
Requires-Dist: pandas
Requires-Dist: matplotlib
Requires-Dist: requests
Requires-Dist: numpy
Requires-Dist: scipy
Requires-Dist: intermine
